popcorn_diskpop/__init__.py
popcorn_diskpop/popcorn_diskpop.py
popcorn_diskpop-0.0.14.dist-info/LICENSE
popcorn_diskpop-0.0.14.dist-info/METADATA
popcorn_diskpop-0.0.14.dist-info/WHEEL
popcorn_diskpop-0.0.14.dist-info/top_level.txt
popcorn_diskpop-0.0.14.dist-info/RECORD
