Metadata-Version: 2.1
Name: popcorn-diskpop
Version: 0.0.14
Summary: Popcorn - tool to analyse Diskpop output
Home-page: https://bitbucket.org/diskpopteam/diskpop/src/master/
Author: Alice Somigliana, Claudia Toci, Giovanni Rosotti
Author-email: alice.somigliana@eso.org
License: GPL
Platform: UNKNOWN
Requires-Dist: numpy (==1.21)
Requires-Dist: pandas
